setup.cfg
setup.py
autogit_client.egg-info/PKG-INFO
autogit_client.egg-info/SOURCES.txt
autogit_client.egg-info/dependency_links.txt
autogit_client.egg-info/entry_points.txt
autogit_client.egg-info/top_level.txt
autogit_daemon/__init__.py
autogit_daemon/autogit_client.py
autogit_daemon/daemon.py
autogit_daemon/test_utils.py
autogit_daemon/utils.py