Metadata-Version: 1.1
Name: autogit-client
Version: 0.1.5
Summary: A Daemon for Autogit Client
Home-page: https://gitlab.vimlabs.com/vimlabs/autogit.io-daemon
Author: Vimlabs
Author-email: neiell@vimlabs.com
License: UNKNOWN
Download-URL: https://gitlab.vimlabs.com/vimlabs/autogit.io-daemon/repository/master/archive.tar.gz
Keywords: autogit,autogit-daemon,autogit-client,vimlabs,auto-deploy,deploy automation
Platform: UNKNOWN
